{"job_config":{"name":null,"steps":[{"type":"udf","name":null,"metadata":null,"ignore_chunk_error":false,"udf":{"name":"visitors_arrival","type":"geopandas_v2","headers":[],"metadata":{"fused:mcp":{"description":"\nName: visitor_info\nPurpose and Functionality:\nThe UDF 'visitor_info' retrieves visitor arrival data for a specified year from a CSV file. If no year is provided, it defaults to 1964. The function reads the dataset, filters the data based on the requested year, and returns a DataFrame containing visitor statistics.\n\nInput Parameters:\n- year (int, optional): The year for which visitor arrival data is requested. Defaults to 1964.\n\nOutput:\nThe function returns a Pandas DataFrame containing visitor arrival details for the specified year. If no records exist for the given year, an empty DataFrame with the appropriate column structure is returned.\n\nTechnical Details and Limitations:\n- The function reads data from a local CSV file ('visitors_arrival.csv'). The CSV file must be available in the expected format.\n- If the CSV file is missing or corrupt, the function may raise an error.\n- The function ensures that the 'Year' column is treated as an integer for filtering.\n- If an invalid year (e.g., a non-integer string) is provided, the function may fail unless additional validation is implemented.\n- The function caches the CSV file using fused.cache to improve efficiency.\n    ","parameters":[{"name":"year","type":"integer","default":1964,"description":"The year for which visitor arrival data is requested. Defaults to 1964."}]},"fused:slug":"visitors_arrival","fused:name":"visitors_arrival"},"table_schema":null,"entrypoint":"visitor_info","cache_max_age":null,"parameters":{},"original_headers":"","source":"visitors_arrival.py"},"input":null}],"metadata":null}}